{
    "title": "电影港",
    "author": "香雅情",
    "Headers": "PC_UA",
    "Coding_format": "",
    "PicNeedProxy": "1",
    "homeContent": "0",
    "firstpage": "",
    "class_url": "https://www.dyg123.net/{cateId}/index_{catePg}.html[firstPage=https://www.dyg123.net/{cateId}/index.html",
    "class_name": "电影&电视剧&综艺节目",
    "class_value": "dy&dsj&zyjm",
    "filterdata": {},
    "cat_mode": "1",
    "cat_arr_rule": ".index-area&&li",
    "cat_is_jsoup": "1",
    "cat_title": "a&&title",
    "cat_url": "a&&href",
    "cat_pic": "img&&data-original",
    "cat_subtitle": "i&&Text",
    "cat_prefix": "",
    "cat_suffix": "",
    "SHeaders": "User-Agent$MOBILE_UA",
    "search_url": "https://www.dyg123.net/e/search/index.php;post",
    "sea_PtBody": "keyboard={wd}&submit=搜 索&show=title,zhuyan&tempid=1",
    "search_mode": "1",
    "sea_arr_rule": ".index-area&&ul&&li",
    "sea_is_jsoup": "1",
    "sea_pic": "img&&data-original",
    "sea_title": "a&&title",
    "sea_url": "a&&href",
    "sea_subtitle": "i&&Text",
    "search_prefix": "",
    "search_suffix": "",
    "force_play": "0",
    "play_prefix": "",
    "play_suffix": "",
    "play_header": "",
    "proj_is_jsoup": "0",
    "proj_cate": "",
    "proj_year": "",
    "proj_area": "",
    "proj_actor": "演　　员&&</",
    "proj_plot": "简　　介&&</",
    "tab_arr_rule": ".ct-l",
    "tab_title": "strong&&Text",
    "list_arr_rule": "tbody",
    "epi_arr_rule": "tr&&td",
    "epi_title": "a&&Text",
    "epi_url": "a&&href",
    "epi_reverse": "0",
    "epiurl_prefix": "",
    "epiurl_suffix": "",
    "Anal_MacPlayer": "0",
    "ManualSniffer": "0",
    "VideoFormat": ".mp4#.m3u8#.flv",
    "VideoFilter": ".html#=http"
}